AUTHORS.rst
HISTORY.rst
LICENSE
MANIFEST.in
README.rst
setup.py
pyps/__init__.py
pyps/_des.py
pyps/_pyps.py
pyps.egg-info/PKG-INFO
pyps.egg-info/SOURCES.txt
pyps.egg-info/dependency_links.txt
pyps.egg-info/not-zip-safe
pyps.egg-info/requires.txt
pyps.egg-info/top_level.txt