Metadata-Version: 1.1
Name: pyps
Version: 0.6.0
Summary: A pure python implentation for communicating to Adobe Photoshop
Home-page: https://github.com/theiviaxx/photoshopConnection
Author: Brett Dixon
Author-email: theiviaxx@gmail.com
License: MIT
Platform: any
Classifier: Intended Audience :: Developers
Classifier: License :: OSI Approved :: MIT License
Classifier: Natural Language :: English
Classifier: Programming Language :: Python :: 2
Classifier: Programming Language :: Python :: 2.6
Classifier: Programming Language :: Python :: 2.7
Classifier: Programming Language :: Python :: 3
Classifier: Programming Language :: Python :: 3.6
Classifier: Programming Language :: Python :: 3.7
